{
  "$schema": "https://developer.microsoft.com/json-schemas/fabric/item/report/definition/visualContainer/2.8.0/schema.json",
  "name": "df4796df3a5919f59d16",
  "position": {
    "x": 1017.5187314422894,
    "y": 846.79411207277781,
    "z": 21000,
    "height": 218.5275127929749,
    "width": 821.754501231916,
    "tabOrder": 20000
  },
  "visual": {
    "visualType": "pivotTable",
    "query": {
      "queryState": {
        "Columns": {
          "projections": [
            {
              "field": {
                "Column": {
                  "Expression": {
                    "SourceRef": {
                      "Entity": "Fact"
                    }
                  },
                  "Property": "Key_Dim_2"
                }
              },
              "queryRef": "Fact.Key_Dim_2",
              "nativeQueryRef": "Key_Dim_2",
              "active": true,
              "displayName": "Key_Dim_2"
            }
          ],
          "fieldParameters": [
            {
              "parameterExpr": {
                "Column": {
                  "Expression": {
                    "SourceRef": {
                      "Entity": "Select 2nd Dimension"
                    }
                  },
                  "Property": "Select 2nd Dimension"
                }
              },
              "index": 0,
              "length": 1
            }
          ]
        },
        "Rows": {
          "projections": [
            {
              "field": {
                "Column": {
                  "Expression": {
                    "SourceRef": {
                      "Entity": "Fact"
                    }
                  },
                  "Property": "Key_Dim_1"
                }
              },
              "queryRef": "Fact.Key_Dim_1",
              "nativeQueryRef": "Key_Dim_1",
              "active": true,
              "displayName": "Key_Dim_1"
            }
          ],
          "fieldParameters": [
            {
              "parameterExpr": {
                "Column": {
                  "Expression": {
                    "SourceRef": {
                      "Entity": "Select Dimension"
                    }
                  },
                  "Property": "Select Dimension"
                }
              },
              "index": 0,
              "length": 1
            }
          ]
        },
        "Values": {
          "projections": [
            {
              "field": {
                "Measure": {
                  "Expression": {
                    "SourceRef": {
                      "Entity": "Fact"
                    }
                  },
                  "Property": "DAX_SUM_Measure_1"
                }
              },
              "queryRef": "Fact.DAX_SUM_Measure_1",
              "nativeQueryRef": "SUM_Measure_1",
              "displayName": "SUM_Measure_1"
            }
          ],
          "fieldParameters": [
            {
              "parameterExpr": {
                "Column": {
                  "Expression": {
                    "SourceRef": {
                      "Entity": "Select Measure"
                    }
                  },
                  "Property": "Select Measure"
                }
              },
              "index": 0,
              "length": 1
            }
          ]
        }
      },
      "sortDefinition": {
        "isDefaultSort": true
      }
    },
    "visualContainerObjects": {
      "title": [
        {
          "properties": {
            "titleWrap": {
              "expr": {
                "Literal": {
                  "Value": "true"
                }
              }
            },
            "fontFamily": {
              "expr": {
                "Literal": {
                  "Value": "'''Segoe UI Semibold'', wf_segoe-ui_semibold, helvetica, arial, sans-serif'"
                }
              }
            },
            "fontSize": {
              "expr": {
                "Literal": {
                  "Value": "12D"
                }
              }
            }
          }
        }
      ],
      "background": [
        {
          "properties": {
            "show": {
              "expr": {
                "Literal": {
                  "Value": "true"
                }
              }
            },
            "transparency": {
              "expr": {
                "Literal": {
                  "Value": "0D"
                }
              }
            }
          }
        }
      ],
      "border": [
        {
          "properties": {
            "show": {
              "expr": {
                "Literal": {
                  "Value": "true"
                }
              }
            },
            "color": {
              "solid": {
                "color": {
                  "expr": {
                    "ThemeDataColor": {
                      "ColorId": 0,
                      "Percent": 0
                    }
                  }
                }
              }
            },
            "radius": {
              "expr": {
                "Literal": {
                  "Value": "25D"
                }
              }
            },
            "width": {
              "expr": {
                "Literal": {
                  "Value": "1D"
                }
              }
            }
          }
        }
      ],
      "dropShadow": [
        {
          "properties": {
            "show": {
              "expr": {
                "Literal": {
                  "Value": "true"
                }
              }
            },
            "color": {
              "solid": {
                "color": {
                  "expr": {
                    "Literal": {
                      "Value": "'#E6E6E6'"
                    }
                  }
                }
              }
            }
          }
        }
      ]
    },
    "drillFilterOtherVisuals": true
  }
}